<measure>
  <schema_version>3.0</schema_version>
  <name>process_hvac_sizing</name>
  <uid>6cd70740-6ca3-4575-8b1e-663976e254d0</uid>
  <version_id>24ea12bc-e054-461f-be0d-07a9db83e42f</version_id>
  <version_modified>20180127T224432Z</version_modified>
  <xml_checksum>356BE47F</xml_checksum>
  <class_name>ProcessHVACSizing</class_name>
  <display_name>Set Residential HVAC Sizing</display_name>
  <description>This measure performs HVAC sizing calculations via ACCA Manual J/S, as well as sizing calculations for ground source heat pumps and dehumidifiers. See https://github.com/NREL/OpenStudio-BEopt#workflows for supported workflows using this measure.</description>
  <modeler_description>This measure assigns HVAC heating/cooling capacities, airflow rates, etc.</modeler_description>
  <arguments>
    <argument>
      <name>show_debug_info</name>
      <display_name>Show Debug Info</display_name>
      <description>Displays various intermediate calculation results.</description>
      <type>Boolean</type>
      <required>true</required>
      <model_dependent>false</model_dependent>
      <default_value>false</default_value>
      <choices>
        <choice>
          <value>true</value>
          <display_name>true</display_name>
        </choice>
        <choice>
          <value>false</value>
          <display_name>false</display_name>
        </choice>
      </choices>
    </argument>
  </arguments>
  <outputs/>
  <provenances/>
  <tags>
    <tag>HVAC.HVAC Controls</tag>
  </tags>
  <attributes>
    <attribute>
      <name>Measure Type</name>
      <value>ModelMeasure</value>
      <datatype>string</datatype>
    </attribute>
    <attribute>
      <name>Intended Software Tool</name>
      <value>Apply Measure Now</value>
      <datatype>string</datatype>
    </attribute>
    <attribute>
      <name>Intended Software Tool</name>
      <value>OpenStudio Application</value>
      <datatype>string</datatype>
    </attribute>
    <attribute>
      <name>Intended Software Tool</name>
      <value>Parametric Analysis Tool</value>
      <datatype>string</datatype>
    </attribute>
  </attributes>
  <files>
    <file>
      <filename>USA_CO_Denver_Intl_AP_725650_TMY3.ddy</filename>
      <filetype>ddy</filetype>
      <usage_type>test</usage_type>
      <checksum>FB253570</checksum>
    </file>
    <file>
      <filename>USA_CO_Denver_Intl_AP_725650_TMY3.epw</filename>
      <filetype>epw</filetype>
      <usage_type>test</usage_type>
      <checksum>E23378AA</checksum>
    </file>
    <file>
      <filename>USA_CA_Los.Angeles.Intl.AP.722950_TMY3.ddy</filename>
      <filetype>ddy</filetype>
      <usage_type>test</usage_type>
      <checksum>B06731CA</checksum>
    </file>
    <file>
      <filename>USA_CA_Los.Angeles.Intl.AP.722950_TMY3.epw</filename>
      <filetype>epw</filetype>
      <usage_type>test</usage_type>
      <checksum>2E4F946B</checksum>
    </file>
    <file>
      <filename>USA_GA_Atlanta-Hartsfield-Jackson.Intl.AP.722190_TMY3.ddy</filename>
      <filetype>ddy</filetype>
      <usage_type>test</usage_type>
      <checksum>79607561</checksum>
    </file>
    <file>
      <filename>USA_GA_Atlanta-Hartsfield-Jackson.Intl.AP.722190_TMY3.epw</filename>
      <filetype>epw</filetype>
      <usage_type>test</usage_type>
      <checksum>F0AA8FA7</checksum>
    </file>
    <file>
      <filename>psychrometrics.rb</filename>
      <filetype>rb</filetype>
      <usage_type>resource</usage_type>
      <checksum>11E27E42</checksum>
    </file>
    <file>
      <filename>unit_conversions.rb</filename>
      <filetype>rb</filetype>
      <usage_type>resource</usage_type>
      <checksum>31924A51</checksum>
    </file>
    <file>
      <filename>weather.rb</filename>
      <filetype>rb</filetype>
      <usage_type>resource</usage_type>
      <checksum>82988A63</checksum>
    </file>
    <file>
      <filename>util.rb</filename>
      <filetype>rb</filetype>
      <usage_type>resource</usage_type>
      <checksum>293A1428</checksum>
    </file>
    <file>
      <filename>geometry.rb</filename>
      <filetype>rb</filetype>
      <usage_type>resource</usage_type>
      <checksum>B0C5E88A</checksum>
    </file>
    <file>
      <filename>schedules.rb</filename>
      <filetype>rb</filetype>
      <usage_type>resource</usage_type>
      <checksum>A299BFF0</checksum>
    </file>
    <file>
      <filename>hvac.rb</filename>
      <filetype>rb</filetype>
      <usage_type>resource</usage_type>
      <checksum>5E23CBEA</checksum>
    </file>
    <file>
      <filename>constants.rb</filename>
      <filetype>rb</filetype>
      <usage_type>resource</usage_type>
      <checksum>A904261C</checksum>
    </file>
    <file>
      <filename>SFD_HVACSizing_Load_2story_CS_GRG_FA.osm</filename>
      <filetype>osm</filetype>
      <usage_type>test</usage_type>
      <checksum>DDD4C087</checksum>
    </file>
    <file>
      <filename>SFD_HVACSizing_Load_2story_FB_GRG_FA.osm</filename>
      <filetype>osm</filetype>
      <usage_type>test</usage_type>
      <checksum>F8306E5D</checksum>
    </file>
    <file>
      <filename>SFD_HVACSizing_Load_2story_S_GRG_FA.osm</filename>
      <filetype>osm</filetype>
      <usage_type>test</usage_type>
      <checksum>70561A05</checksum>
    </file>
    <file>
      <filename>SFD_HVACSizing_Load_2story_UB_GRG_FA.osm</filename>
      <filetype>osm</filetype>
      <usage_type>test</usage_type>
      <checksum>B5A5D4ED</checksum>
    </file>
    <file>
      <filename>SFD_HVACSizing_Load_2story_CS_GRG_FA_ASHP_DuctsInCS.osm</filename>
      <filetype>osm</filetype>
      <usage_type>test</usage_type>
      <checksum>5AD92F16</checksum>
    </file>
    <file>
      <filename>SFD_HVACSizing_Load_2story_CS_GRG_FA_ASHP_DuctsInGRG.osm</filename>
      <filetype>osm</filetype>
      <usage_type>test</usage_type>
      <checksum>3C9F303D</checksum>
    </file>
    <file>
      <filename>SFD_HVACSizing_Load_2story_CS_GRG_FA_ASHP_DuctsInLiv.osm</filename>
      <filetype>osm</filetype>
      <usage_type>test</usage_type>
      <checksum>6C691F62</checksum>
    </file>
    <file>
      <filename>SFD_HVACSizing_Load_2story_FB_GRG_FA_ASHP_DuctsInFB.osm</filename>
      <filetype>osm</filetype>
      <usage_type>test</usage_type>
      <checksum>93C8771B</checksum>
    </file>
    <file>
      <filename>SFD_HVACSizing_Load_2story_UB_GRG_FA_ASHP_DuctsInUB.osm</filename>
      <filetype>osm</filetype>
      <usage_type>test</usage_type>
      <checksum>3D79CD1B</checksum>
    </file>
    <file>
      <filename>SFD_HVACSizing_Equip_BB_Autosize.osm</filename>
      <filetype>osm</filetype>
      <usage_type>test</usage_type>
      <checksum>4115069A</checksum>
    </file>
    <file>
      <filename>SFD_HVACSizing_Equip_GF_AC1_Autosize.osm</filename>
      <filetype>osm</filetype>
      <usage_type>test</usage_type>
      <checksum>2C3BA91A</checksum>
    </file>
    <file>
      <filename>SFD_HVACSizing_Equip_GF_RAC_Autosize.osm</filename>
      <filetype>osm</filetype>
      <usage_type>test</usage_type>
      <checksum>11DFB458</checksum>
    </file>
    <file>
      <filename>SFD_HVACSizing_Equip_GF_AC1_Fixed.osm</filename>
      <filetype>osm</filetype>
      <usage_type>test</usage_type>
      <checksum>0CEB5EC3</checksum>
    </file>
    <file>
      <filename>SFD_HVACSizing_Equip_BB_Fixed.osm</filename>
      <filetype>osm</filetype>
      <usage_type>test</usage_type>
      <checksum>8D624E5A</checksum>
    </file>
    <file>
      <filename>SFD_HVACSizing_Equip_GF_RAC_Fixed.osm</filename>
      <filetype>osm</filetype>
      <usage_type>test</usage_type>
      <checksum>4E3FCEFB</checksum>
    </file>
    <file>
      <filename>SFD_HVACSizing_Equip_Dehumidifier_Auto_Atlanta.osm</filename>
      <filetype>osm</filetype>
      <usage_type>test</usage_type>
      <checksum>4F6CB7BA</checksum>
    </file>
    <file>
      <filename>SFD_HVACSizing_Equip_Dehumidifier_Fixed_Atlanta.osm</filename>
      <filetype>osm</filetype>
      <usage_type>test</usage_type>
      <checksum>6F83DCB9</checksum>
    </file>
    <file>
      <filename>SFD_HVACSizing_Equip_GF_Autosize.osm</filename>
      <filetype>osm</filetype>
      <usage_type>test</usage_type>
      <checksum>2A6D48F5</checksum>
    </file>
    <file>
      <filename>SFD_HVACSizing_Equip_GF_Fixed.osm</filename>
      <filetype>osm</filetype>
      <usage_type>test</usage_type>
      <checksum>B3BEBDD2</checksum>
    </file>
    <file>
      <filename>SFD_HVACSizing_Equip_ASHP1_Autosize_MinTemp.osm</filename>
      <filetype>osm</filetype>
      <usage_type>test</usage_type>
      <checksum>9C256FC6</checksum>
    </file>
    <file>
      <filename>SFD_HVACSizing_Equip_ASHP1_Fixed.osm</filename>
      <filetype>osm</filetype>
      <usage_type>test</usage_type>
      <checksum>3B72E796</checksum>
    </file>
    <file>
      <filename>SFD_HVACSizing_Equip_ElecBoiler_Autosize.osm</filename>
      <filetype>osm</filetype>
      <usage_type>test</usage_type>
      <checksum>2E3DC77E</checksum>
    </file>
    <file>
      <filename>SFD_HVACSizing_Equip_ElecBoiler_Fixed.osm</filename>
      <filetype>osm</filetype>
      <usage_type>test</usage_type>
      <checksum>3C4D001B</checksum>
    </file>
    <file>
      <filename>SFD_HVACSizing_Equip_GSHP_Autosize.osm</filename>
      <filetype>osm</filetype>
      <usage_type>test</usage_type>
      <checksum>91793319</checksum>
    </file>
    <file>
      <filename>SFD_HVACSizing_Equip_GSHP_Fixed.osm</filename>
      <filetype>osm</filetype>
      <usage_type>test</usage_type>
      <checksum>449AF981</checksum>
    </file>
    <file>
      <filename>SFD_HVACSizing_Load_1story_PB_UA_Vented.osm</filename>
      <filetype>osm</filetype>
      <usage_type>test</usage_type>
      <checksum>E1E02158</checksum>
    </file>
    <file>
      <filename>SFD_HVACSizing_Load_1story_PB_UA_Vented_ASHP_DuctsInPB.osm</filename>
      <filetype>osm</filetype>
      <usage_type>test</usage_type>
      <checksum>22C9739D</checksum>
    </file>
    <file>
      <filename>SFD_HVACSizing_Load_1story_PB_UA_Vented_ASHP_DuctsInUA.osm</filename>
      <filetype>osm</filetype>
      <usage_type>test</usage_type>
      <checksum>E352F357</checksum>
    </file>
    <file>
      <filename>SFD_HVACSizing_Load_1story_S_UA_Unvented_NoOverhangs_NoIntShading_ERV.osm</filename>
      <filetype>osm</filetype>
      <usage_type>test</usage_type>
      <checksum>0695295A</checksum>
    </file>
    <file>
      <filename>SFD_HVACSizing_Load_1story_S_UA_Unvented_NoOverhangs_NoIntShading_HRV.osm</filename>
      <filetype>osm</filetype>
      <usage_type>test</usage_type>
      <checksum>5F024754</checksum>
    </file>
    <file>
      <filename>SFD_HVACSizing_Load_1story_S_UA_Unvented_NoOverhangs_NoIntShading_NoMechVent.osm</filename>
      <filetype>osm</filetype>
      <usage_type>test</usage_type>
      <checksum>019FB3F5</checksum>
    </file>
    <file>
      <filename>SFD_HVACSizing_Load_1story_S_UA_Unvented_NoOverhangs_NoIntShading_SupplyMechVent.osm</filename>
      <filetype>osm</filetype>
      <usage_type>test</usage_type>
      <checksum>A7BBACC1</checksum>
    </file>
    <file>
      <filename>SFD_HVACSizing_Load_1story_S_UA_Vented.osm</filename>
      <filetype>osm</filetype>
      <usage_type>test</usage_type>
      <checksum>3267A477</checksum>
    </file>
    <file>
      <filename>SFD_HVACSizing_Load_1story_S_UA_Vented_Atlanta_ExtFinDark.osm</filename>
      <filetype>osm</filetype>
      <usage_type>test</usage_type>
      <checksum>BC7E3C71</checksum>
    </file>
    <file>
      <filename>SFD_HVACSizing_Load_1story_S_UA_Vented_LosAngeles.osm</filename>
      <filetype>osm</filetype>
      <usage_type>test</usage_type>
      <checksum>74E6E131</checksum>
    </file>
    <file>
      <filename>SFD_HVACSizing_Load_1story_S_UA_Unvented_InsRoof.osm</filename>
      <filetype>osm</filetype>
      <usage_type>test</usage_type>
      <checksum>E45A3B68</checksum>
    </file>
    <file>
      <filename>SFD_HVACSizing_Equip_MissingBeds.osm</filename>
      <filetype>osm</filetype>
      <usage_type>test</usage_type>
      <checksum>E8BF9E83</checksum>
    </file>
    <file>
      <filename>SFD_HVACSizing_Equip_ASHPV_Autosize.osm</filename>
      <filetype>osm</filetype>
      <usage_type>test</usage_type>
      <checksum>78F662A2</checksum>
    </file>
    <file>
      <filename>SFD_HVACSizing_Equip_EF_AC2_Autosize.osm</filename>
      <filetype>osm</filetype>
      <usage_type>test</usage_type>
      <checksum>65781269</checksum>
    </file>
    <file>
      <filename>SFD_HVACSizing_Equip_ASHP2_Fixed.osm</filename>
      <filetype>osm</filetype>
      <usage_type>test</usage_type>
      <checksum>C75A26EF</checksum>
    </file>
    <file>
      <filename>SFD_HVACSizing_Equip_ASHPV_Fixed.osm</filename>
      <filetype>osm</filetype>
      <usage_type>test</usage_type>
      <checksum>AC9C6FFF</checksum>
    </file>
    <file>
      <filename>SFD_HVACSizing_Equip_EF_AC2_Fixed.osm</filename>
      <filetype>osm</filetype>
      <usage_type>test</usage_type>
      <checksum>B3212C0D</checksum>
    </file>
    <file>
      <filename>SFD_HVACSizing_Equip_GF_ACV_Autosize.osm</filename>
      <filetype>osm</filetype>
      <usage_type>test</usage_type>
      <checksum>21896D0A</checksum>
    </file>
    <file>
      <filename>SFD_HVACSizing_Equip_ASHP2_Autosize.osm</filename>
      <filetype>osm</filetype>
      <usage_type>test</usage_type>
      <checksum>1B73AC9F</checksum>
    </file>
    <file>
      <filename>SFD_2000sqft_2story_FB_UA.osm</filename>
      <filetype>osm</filetype>
      <usage_type>test</usage_type>
      <checksum>68601D09</checksum>
    </file>
    <file>
      <filename>SFD_2000sqft_2story_FB_UA_Denver.osm</filename>
      <filetype>osm</filetype>
      <usage_type>test</usage_type>
      <checksum>99AAD5C5</checksum>
    </file>
    <file>
      <filename>SFD_HVACSizing_Equip_ASHP1_Autosize.osm</filename>
      <filetype>osm</filetype>
      <usage_type>test</usage_type>
      <checksum>7006DCE5</checksum>
    </file>
    <file>
      <filename>SFD_HVACSizing_Equip_ASHP1_AutosizeForMaxLoad_MinTemp.osm</filename>
      <filetype>osm</filetype>
      <usage_type>test</usage_type>
      <checksum>FC8EBD3E</checksum>
    </file>
    <file>
      <filename>SFD_HVACSizing_Equip_GF_ACV_Fixed.osm</filename>
      <filetype>osm</filetype>
      <usage_type>test</usage_type>
      <checksum>D27C3565</checksum>
    </file>
    <file>
      <filename>SFD_HVACSizing_Equip_GasBoiler_Autosize.osm</filename>
      <filetype>osm</filetype>
      <usage_type>test</usage_type>
      <checksum>154CC02E</checksum>
    </file>
    <file>
      <filename>SFD_HVACSizing_Equip_GasBoiler_Fixed.osm</filename>
      <filetype>osm</filetype>
      <usage_type>test</usage_type>
      <checksum>0A59A1E7</checksum>
    </file>
    <file>
      <filename>SFD_HVACSizing_Equip_MSHP_Autosize.osm</filename>
      <filetype>osm</filetype>
      <usage_type>test</usage_type>
      <checksum>2E662015</checksum>
    </file>
    <file>
      <filename>SFD_HVACSizing_Equip_MSHP_BB_Autosize.osm</filename>
      <filetype>osm</filetype>
      <usage_type>test</usage_type>
      <checksum>F0CF94AD</checksum>
    </file>
    <file>
      <filename>SFD_HVACSizing_Equip_MSHP_AutosizeForMaxLoad.osm</filename>
      <filetype>osm</filetype>
      <usage_type>test</usage_type>
      <checksum>5016E2C8</checksum>
    </file>
    <file>
      <filename>SFD_HVACSizing_Equip_MSHP_Fixed.osm</filename>
      <filetype>osm</filetype>
      <usage_type>test</usage_type>
      <checksum>83ADE0BE</checksum>
    </file>
    <file>
      <filename>SFD_HVACSizing_Equip_MSHP_BB_Fixed.osm</filename>
      <filetype>osm</filetype>
      <usage_type>test</usage_type>
      <checksum>01C59D99</checksum>
    </file>
    <file>
      <filename>MF_HVACSizing_Load_8units_1story_UB.osm</filename>
      <filetype>osm</filetype>
      <usage_type>test</usage_type>
      <checksum>89B78ED2</checksum>
    </file>
    <file>
      <filename>SFA_HVACSizing_Load_4units_1story_FB_UA.osm</filename>
      <filetype>osm</filetype>
      <usage_type>test</usage_type>
      <checksum>2D69691E</checksum>
    </file>
    <file>
      <filename>SFD_HVACSizing_Equip_MSHPDucted_Autosize.osm</filename>
      <filetype>osm</filetype>
      <usage_type>test</usage_type>
      <checksum>D42288CA</checksum>
    </file>
    <file>
      <filename>SFD_HVACSizing_Equip_UnitHeater_AC1_Autosize.osm</filename>
      <filetype>osm</filetype>
      <usage_type>test</usage_type>
      <checksum>6E37B503</checksum>
    </file>
    <file>
      <filename>SFD_HVACSizing_Equip_UnitHeater_AC1_Fixed.osm</filename>
      <filetype>osm</filetype>
      <usage_type>test</usage_type>
      <checksum>093DFF37</checksum>
    </file>
    <file>
      <filename>SFD_HVACSizing_Equip_UnitHeater_Autosize.osm</filename>
      <filetype>osm</filetype>
      <usage_type>test</usage_type>
      <checksum>B625F20D</checksum>
    </file>
    <file>
      <filename>SFD_HVACSizing_Equip_UnitHeater_Fixed.osm</filename>
      <filetype>osm</filetype>
      <usage_type>test</usage_type>
      <checksum>B85A5CDE</checksum>
    </file>
    <file>
      <filename>SFD_HVACSizing_Equip_UnitHeater_Fixed_wFan.osm</filename>
      <filetype>osm</filetype>
      <usage_type>test</usage_type>
      <checksum>E5403B45</checksum>
    </file>
    <file>
      <filename>residential_hvac_sizing_test.rb</filename>
      <filetype>rb</filetype>
      <usage_type>test</usage_type>
      <checksum>6E2B40FA</checksum>
    </file>
    <file>
      <version>
        <software_program>OpenStudio</software_program>
        <identifier>1.11.5</identifier>
        <min_compatible>2.1.2</min_compatible>
      </version>
      <filename>measure.rb</filename>
      <filetype>rb</filetype>
      <usage_type>script</usage_type>
      <checksum>A1D5A697</checksum>
    </file>
  </files>
</measure>
